{
    "name": "messages.get",
    "display": "messages.get",
    "purpose": "Получите сообщение за идентификатором",
    "way": "Получение сообщения за его уникальным номером",

    "request": [
        {
            "name": "token",
            "type": "string",
            "important": true,
            "info": "Данные для авторизации"
        },
        {
            "name": "id",
            "type": "int",
            "important": true,
            "info": "ID сообщения для получения"
        }
    ],
    "answer": [
        {
            "name": "response",
            "type": "array class message",
            "important": false,
            "info": "Запрашиваемое сообщение. False в случае неудачи"
        }
    ]
}